README.md
setup.cfg
setup.py
pylaynii/PYLN_LAYER_SMOOTH.py
pylaynii/__init__.py
pylaynii.egg-info/PKG-INFO
pylaynii.egg-info/SOURCES.txt
pylaynii.egg-info/dependency_links.txt
pylaynii.egg-info/entry_points.txt
pylaynii.egg-info/requires.txt
pylaynii.egg-info/top_level.txt
pylaynii.egg-info/zip-safe