Metadata-Version: 1.0
Name: pylaynii
Version: 0.0.0
Summary: Layer-MRI analysis in python.
Home-page: https://github.com/ofgulban/PyLAYNII
Author: Omer Faruk Gulban
Author-email: faruk.gulban@maastrichtuniversity.nl
License: BSD-3-clause
Keywords: mri,nifti,layer
Platform: UNKNOWN
